{
    "DQ0401": "정악_4박_양청도드리",
    "DQ0402": "정악_4박_타령",
    "DQ0403": "중중모리",
    "DQ0404": "자진모리",
    "DQ0405": "굿거리",
    "DQ0406": "타령",
    "DQ0407": "자진타령",
    "DQ0408": "삼채",
    "DQ0409": "반삼채",
    "DQ0410": "자진삼채",
    "DQ0411": "쩍쩍이굿",
    "DQ0412": "마당삼채",
    "DQ0413": "반길군악",
    "DQ0414": "낙궁",
    "DQ0415": "발뻐드레",
    "DQ0416": "살풀이",
    "QN0401": "휘모리",
    "QN0402": "푸너리",
    "QN0403": "부정",
    "QN0404": "흘림",
    "DQ0301": "세마치(민요)",
    "QN0301": "동살풀이",
    "DQ0601": "세마치(빠른_진양조)",
    "DQ0602": "정악_6박_도드리",
    "DQ0603": "진양조",
    "DQ0604": "긴염불(대풍류)",
    "QN0601": "엇중모리",
    "QN0602": "도살풀이",
    "DQ0801": "정악_8박_절화",
    "QN1202": "중모리",
    "DQ1201": "정악_12박_취타",
    "DQ1202": "길군악",
    "DQ1001": "정악_10박_세령산",
    "DQ1002": "가곡_10박_장단",
    "DQ1003": "푸살",
    "DQ1004": "터벌림",
    "EN1001": "엇모리",
    "EN1002": "좌질굿",
    "EN1003": "육채",
    "EN1004": "올림채",
    "EN1005": "진쇠",
    "DQ1601": "가곡_16박",
    "DQ2001": "정악_20박",
    "NB0001": "오채질굿",
    "NB0002": "가사_장단",
    "NB0003": "시조_장단",
    "NB0004": "우질굿",
    "NB0005": "칠채",
    "NB0006": "진도푸너리",
    "NB0007": "드렁갱이",
    "NB0008": "삼오장",
    "NB0009": "사자풀이",
    "NB0010": "청보",
    "NB0011": "제마수",
    "NB0012": "삼공잽이",
    "NB0013": "기타"
}