{
    "C01": "종묘제례악",
    "C02": "문묘제례악",
    "C03": "관현합주_여민락",
    "C04": "여민락(만_령_해령)",
    "C05": "정읍(수제천)",
    "C06": "동동",
    "C07": "보허자",
    "C08": "낙양춘",
    "C09": "취타",
    "C10": "대취타",
    "C11": "궁중음악_기타",
    "E01": "영산회상",
    "E02": "자진한잎",
    "E03": "보허사",
    "E04": "도드리",
    "E05": "가곡",
    "E06": "가사",
    "E07": "시조",
    "E08": "풍류음악_기타",
    "F01": "대풍류",
    "F02": "산조",
    "F03": "시나위",
    "F04": "풍물놀이",
    "F05": "사물놀이",
    "F06": "민요",
    "F07": "잡가",
    "F08": "판소리",
    "F09": "단가",
    "F10": "가야금병창",
    "F11": "범패",
    "F12": "창극",
    "F13": "무가",
    "F14": "민속악_기타",
    "CR1": "전통적_창작국악",
    "CR2": "현대적_창작국악",
    "FS1": "클래식_퓨전국악",
    "FS2": "팝_퓨전국악",
    "FS3": "월드_퓨전국악"
}